yuquedd/__init__.py
yuquedd/cli.py
yuquedd/const.py
yuquedd/service.py
yuquedd-1.0.3.dist-info/entry_points.txt
yuquedd-1.0.3.dist-info/LICENSE
yuquedd-1.0.3.dist-info/METADATA
yuquedd-1.0.3.dist-info/WHEEL
yuquedd-1.0.3.dist-info/RECORD
