Metadata-Version: 2.1
Name: yuquedd
Version: 1.0.3
Summary: Tool for converting yuque.com knowledge base documents to markdown documents.
Home-page: https://github.com/gupingan/yuquedd
License: MIT
Author: gupingan
Author-email: g332920287@foxmail.com
Requires-Python: >=3.8
Classifier: License :: OSI Approved :: MIT License
Classifier: Programming Language :: Python :: 3
Classifier: Programming Language :: Python :: 3.8
Classifier: Programming Language :: Python :: 3.9
Classifier: Programming Language :: Python :: 3.10
Classifier: Programming Language :: Python :: 3.11
Requires-Dist: click (>=8.1.7,<9.0.0)
Requires-Dist: lakedoc (>=1.0.4,<2.0.0)
Requires-Dist: lxml (>=5.2.2,<6.0.0)
Requires-Dist: requests (>=2.32.3,<3.0.0)
Project-URL: Documentation, https://github.com/gupingan/yuquedd
Project-URL: Repository, https://github.com/gupingan/yuquedd
